{
  "name": "_ab_thr_pack",
  "type": "package",
  "blockId": "BVBRgFcmNcrqajJWr5wP4",
  "source": {
    "https": null,
    "ssh": null,
    "branch": "block__ab_thr_pack"
  },
  "parentBlockIDs": [
    "1pGb9GOPd_kYxE9trywsr"
  ],
  "isPublic": true,
  "supportedAppblockVersions": [
    "1.0.0"
  ],
  "repoType": "mono",
  "dependencies": {
    "_ab_tp_fn": {
      "directory": "_ab_tp_fn",
      "versionId": "UjTUJgQpzzq7JDtvFkBeH",
      "version": "0.0.1"
    }
  },
  "version": "0.0.1",
  "versionId": "kOulR4zSdfy_B7sl7wkJU",
  "variantOf": "kOulR4zSdfy_B7sl7wkJU"
}